{"type": "Feature", "id": 12524035, "properties": {"woe:id": 12524035, "woe:parent_id": 57424, "woe:name": "Punta Gorda Airport", "woe:placetype": 14, "woe:placetype_name": "Airport", "woe:lang": "ENG", "iso:country": "BZ", "meta:provider": ["geoplanet:7.3.1", "geoplanet:7.3.2", "geoplanet:7.4.0", "geoplanet:7.4.1", "geoplanet:7.5.1", "geoplanet:7.5.2", "geoplanet:7.6.0", "geoplanet:7.8.1", "geoplanet:7.9.0", "geoplanet:7.10.0", "geoplanet:8.0.0", "woeplanet:8.0.0"], "meta:indexed": "2020-08-20T20:26:37.299157", "woe:alias_ENG_V": ["PND Airport", "PND", "Pta Gorda Airport"], "meta:updated": "2020-08-22T01:58:48.201713", "woe:hierarchy": {"continent": 24865672, "country": 23424760, "town": 0, "planet": 1, "county": 0, "suburb": 0, "state": 2344799, "region": 0, "localadmin": 0}, "woe:timezone_id": 28350740, "woe:hash": "d4bgdde8p691", "woe:centroid": [-88.83033, 16.097731], "geom:latitude": 16.097731, "geom:longitude": -88.83033, "geom:hash": "d4bgdde8p691", "woe:latitude": 16.097731, "geom:centroid": [-88.83033, 16.097731], "woe:longitude": -88.83033, "woe:repo": "woeplanet-airport-bz"}, "geometry": {"coordinates": [-88.83033, 16.097731], "type": "Point"}}